{
    "version": "0.29.4",
    "architecture": {
        "64bit": {
            "url": "https://github.com/Qovery/qovery-cli/releases/download/v0.29.4/qovery-cli_0.29.4_windows_amd64.zip",
            "bin": [
                "qovery.exe"
            ],
            "hash": "ee7355d60477354376cc3e6c848f5bff75a2c8e80fb48c9ef3de035b4c68a9d4"
        }
    },
    "homepage": "https://docs.qovery.com",
    "license": "GPL3",
    "description": "Deploy modern application in seconds",
    "persist": [
        "data",
        "config.toml"
    ]
}