{
    "version": "1.23.0",
    "architecture": {
        "64bit": {
            "url": "https://github.com/Qovery/qovery-cli/releases/download/v1.23.0/qovery-cli_1.23.0_windows_amd64.zip",
            "bin": [
                "qovery.exe"
            ],
            "hash": "7810c799113a00a556329b7d3b2da889af8bb4803987254f1e363519b6f5c491"
        },
        "arm64": {
            "url": "https://github.com/Qovery/qovery-cli/releases/download/v1.23.0/qovery-cli_1.23.0_windows_arm64.zip",
            "bin": [
                "qovery.exe"
            ],
            "hash": "b98108658ef47ecee283afe440c682c53b1590800f8ab115a320849d60290a09"
        }
    },
    "homepage": "https://docs.qovery.com",
    "license": "GPL3",
    "description": "Deploy modern application in seconds",
    "persist": [
        "data",
        "config.toml"
    ]
}