{
    "version": "0.40.5",
    "architecture": {
        "64bit": {
            "url": "https://github.com/Qovery/qovery-cli/releases/download/v0.40.5/qovery-cli_0.40.5_windows_amd64.zip",
            "bin": [
                "qovery.exe"
            ],
            "hash": "3f1c212b236e7f4c580b6dcdc7311b5b8956e463541791dc7d6671e868d37661"
        }
    },
    "homepage": "https://docs.qovery.com",
    "license": "GPL3",
    "description": "Deploy modern application in seconds",
    "persist": [
        "data",
        "config.toml"
    ]
}